wagtail_embed_videos/__init__.py
wagtail_embed_videos/admin.py
wagtail_embed_videos/admin_urls.py
wagtail_embed_videos/apps.py
wagtail_embed_videos/blocks.py
wagtail_embed_videos/edit_handlers.py
wagtail_embed_videos/forms.py
wagtail_embed_videos/models.py
wagtail_embed_videos/wagtail_hooks.py
wagtail_embed_videos/widgets.py
wagtail_embed_videos/migrations/0001_initial.py
wagtail_embed_videos/migrations/0002_auto_20180822_0945.py
wagtail_embed_videos/migrations/__init__.py
wagtail_embed_videos/static/wagtail_embed_videos/js/embed-video-chooser.js
wagtail_embed_videos/templates/wagtail_embed_videos/chooser/chooser.html
wagtail_embed_videos/templates/wagtail_embed_videos/chooser/chooser.js
wagtail_embed_videos/templates/wagtail_embed_videos/chooser/embed_video_chosen.js
wagtail_embed_videos/templates/wagtail_embed_videos/chooser/results.html
wagtail_embed_videos/templates/wagtail_embed_videos/chooser/select_format.html
wagtail_embed_videos/templates/wagtail_embed_videos/chooser/select_format.js
wagtail_embed_videos/templates/wagtail_embed_videos/edit_handlers/embed_video_chooser_panel.html
wagtail_embed_videos/templates/wagtail_embed_videos/embed_videos/add.html
wagtail_embed_videos/templates/wagtail_embed_videos/embed_videos/confirm_delete.html
wagtail_embed_videos/templates/wagtail_embed_videos/embed_videos/edit.html
wagtail_embed_videos/templates/wagtail_embed_videos/embed_videos/index.html
wagtail_embed_videos/templates/wagtail_embed_videos/embed_videos/results.html
wagtail_embed_videos/templates/wagtail_embed_videos/embed_videos/usage.html
wagtail_embed_videos/templates/wagtail_embed_videos/widgets/embed_video_chooser.html
wagtail_embed_videos/tests/__init__.py
wagtail_embed_videos/tests/settings.py
wagtail_embed_videos/tests/test_model.py
wagtail_embed_videos/views/__init__.py
wagtail_embed_videos/views/chooser.py
wagtail_embed_videos/views/embed_videos.py
wagtail_embedvideos3-0.4.3.dist-info/AUTHORS.rst
wagtail_embedvideos3-0.4.3.dist-info/LICENSE.txt
wagtail_embedvideos3-0.4.3.dist-info/METADATA
wagtail_embedvideos3-0.4.3.dist-info/WHEEL
wagtail_embedvideos3-0.4.3.dist-info/top_level.txt
wagtail_embedvideos3-0.4.3.dist-info/RECORD
