Metadata-Version: 2.1
Name: wagtail-embedvideos3
Version: 0.4.3
Summary: Embed Videos for Wagtail CMS.
Home-page: https://github.com/olksndrdevhub/wagtail-embed-videos3
Author: InfoPortugal S.A.
Author-email: suporte24@infoportugal.com
Maintainer: Romaniuk Oleksandr
Maintainer-email: oleksandr.romaniuk@protonmail.com
License: New BSD
Platform: UNKNOWN
Classifier: Programming Language :: Python
Classifier: Programming Language :: Python :: 2.6
Classifier: Programming Language :: Python :: 2.7
Classifier: Programming Language :: Python :: 3
Classifier: Programming Language :: Python :: 3.2
Classifier: Programming Language :: Python :: 3.3
Classifier: Programming Language :: Python :: 3.4
Classifier: Programming Language :: Python :: 3.5
Classifier: Programming Language :: Python :: 3.6
Classifier: Programming Language :: Python :: 3.8
Classifier: Operating System :: OS Independent
Classifier: Development Status :: 5 - Production/Stable
Classifier: Environment :: Web Environment
Classifier: Intended Audience :: Developers
Classifier: Framework :: Django
Classifier: License :: OSI Approved :: BSD License
Requires-Dist: wagtail (>=2.0)
Requires-Dist: django-embed-video (>=1.4)
Requires-Dist: six (>=1.15.0)
